m3query/__init__.py
m3query/__init__.py.bak
m3query/__init__.py~
m3query/jt400.jar
m3query-0.1.3.dist-info/WHEEL
m3query-0.1.3.dist-info/METADATA
m3query-0.1.3.dist-info/RECORD
